dttxml/__init__.py
dttxml/__main__.py
dttxml/access.py
dttxml/dtt2bunch.py
dttxml/dtt2hdf.py
dttxml/parse.py
dttxml/parse_coefficients.py
dttxml/parse_spectrum.py
dttxml/parse_timeseries.py
dttxml/parse_transfer.py
dttxml/version.py
dttxml-1.1.8.dist-info/licenses/LICENSE
dttxml-1.1.8.dist-info/METADATA
dttxml-1.1.8.dist-info/WHEEL
dttxml-1.1.8.dist-info/entry_points.txt
dttxml-1.1.8.dist-info/top_level.txt
dttxml-1.1.8.dist-info/RECORD
