Metadata-Version: 2.4
Name: dttxml
Version: 1.1.8
Summary: Extract data from LIGO Diagnostics test tools XML format. Formerly dtt2hdf.
Author-email: Lee McCuller <Lee.McCuller@ligo.org>
Maintainer-email: Erik von Reis <erik.vonreis@ligo.org>
License-Expression: Apache-2.0
Project-URL: Homepage, https://git.ligo.org/cds/dttxml
Keywords: LIGO,dtt,diagnostics,file-reader
Classifier: Operating System :: OS Independent
Classifier: Programming Language :: Python
Classifier: Programming Language :: Python :: 3
Classifier: Topic :: Software Development :: Libraries :: Python Modules
License-File: LICENSE
Requires-Dist: numpy
Requires-Dist: h5py
Requires-Dist: declarative>=1.3.0
Dynamic: license-file
